{
  "last_attempt_at": "2026-06-23T12:08:27.318438",
  "last_success_at": "2026-06-23T12:08:27.761203",
  "last_error_at": "2026-06-04T20:51:39.532215",
  "last_error_type": null,
  "consecutive_failures": 0,
  "last_refreshed_symbols": [
    "MTEX",
    "MTG",
    "MTH",
    "MTL",
    "MTLS",
    "MTN",
    "MTNB",
    "MTRN",
    "MTRX",
    "MTSI",
    "MTUS",
    "MTVA",
    "MTW",
    "MTX",
    "MTZ",
    "MU",
    "MUR",
    "MUSA",
    "MUX",
    "MVBF"
  ],
  "refresh_queue_size": 0,
  "is_refreshing": false
}